<?xml version="1.0" encoding="UTF-8"?>
<objects serializationModel="Studio.02.01.00">
	<object class="ParameterPreset" id="{06e64dba-e76d-4345-9475-2d14fdf85a02}">
		<property name="name">
			<value>Gain_17</value>
		</property>
		<relationship name="folder">
			<destination>{560730e1-b882-47d8-9628-071b96244d64}</destination>
		</relationship>
		<relationship name="parameter">
			<destination>{d7ab7a7e-8f25-4659-8d68-f52a5f059644}</destination>
		</relationship>
	</object>
	<object class="GameParameter" id="{d7ab7a7e-8f25-4659-8d68-f52a5f059644}">
		<property name="isGlobal">
			<value>true</value>
		</property>
		<property name="initialValue">
			<value>0</value>
		</property>
		<property name="isExposedRecursively">
			<value>false</value>
		</property>
	</object>
</objects>
