<?xml version="1.0" encoding="UTF-8"?>
<objects serializationModel="Studio.02.01.00">
	<object class="ParameterPreset" id="{62f015f3-215d-4f0e-98d9-5e9903eca646}">
		<property name="name">
			<value>DelayWet_9</value>
		</property>
		<relationship name="folder">
			<destination>{560730e1-b882-47d8-9628-071b96244d64}</destination>
		</relationship>
		<relationship name="parameter">
			<destination>{55d1d0da-9782-4fa5-b848-7212310424d1}</destination>
		</relationship>
	</object>
	<object class="GameParameter" id="{55d1d0da-9782-4fa5-b848-7212310424d1}">
		<property name="isGlobal">
			<value>true</value>
		</property>
		<property name="initialValue">
			<value>0</value>
		</property>
		<property name="isExposedRecursively">
			<value>false</value>
		</property>
	</object>
</objects>
