<?xml version="1.0" encoding="UTF-8"?>
<objects serializationModel="Studio.02.01.00">
	<object class="ParameterPreset" id="{a1457db7-5b37-40cd-8c2b-5414163ab342}">
		<property name="name">
			<value>Gain_4</value>
		</property>
		<relationship name="folder">
			<destination>{560730e1-b882-47d8-9628-071b96244d64}</destination>
		</relationship>
		<relationship name="parameter">
			<destination>{e8d68699-f7b9-486d-823f-b2ca83437047}</destination>
		</relationship>
	</object>
	<object class="GameParameter" id="{e8d68699-f7b9-486d-823f-b2ca83437047}">
		<property name="isGlobal">
			<value>true</value>
		</property>
		<property name="initialValue">
			<value>0</value>
		</property>
		<property name="isExposedRecursively">
			<value>false</value>
		</property>
	</object>
</objects>
